<?xml version="1.0" encoding="utf-8"?>
<RestrictedAreas>
	<Areas>
		<RestrictedArea Type="Restricted" Name="HC (P)-2" AltitudeFloor="0" AltitudeCeiling="10000"
			DAIWEnabled="false" LinePattern="Solid">
			<Area>
				+02.044920+045.336415/
				+02.044864+045.337119/
				+02.044864+045.337119/
				+02.044690+045.337803/
				+02.044690+045.337803/
				+02.044402+045.338448/
				+02.044402+045.338448/
				+02.044009+045.339036/
				+02.044009+045.339036/
				+02.043521+045.339549/
				+02.043521+045.339549/
				+02.042953+045.339973/
				+02.042953+045.339973/
				+02.042321+045.340295/
				+02.042321+045.340295/
				+02.041643+045.340506/
				+02.041643+045.340506/
				+02.040940+045.340601/
				+02.040940+045.340601/
				+02.040230+045.340576/
				+02.040230+045.340576/
				+02.039535+045.340432/
				+02.039535+045.340432/
				+02.038874+045.340173/
				+02.038874+045.340173/
				+02.038266+045.339807/
				+02.038266+045.339807/
				+02.037730+045.339345/
				+02.037730+045.339345/
				+02.037280+045.338798/
				+02.037280+045.338798/
				+02.036929+045.338185/
				+02.036929+045.338185/
				+02.036688+045.337521/
				+02.036688+045.337521/
				+02.036563+045.336826/
				+02.036563+045.336826/
				+02.036558+045.336120/
				+02.036558+045.336120/
				+02.036673+045.335423/
				+02.036673+045.335423/
				+02.036905+045.334756/
				+02.036905+045.334756/
				+02.037247+045.334138/
				+02.037247+045.334138/
				+02.037690+045.333585/
				+02.037690+045.333585/
				+02.038219+045.333115/
				+02.038219+045.333115/
				+02.038821+045.332741/
				+02.038821+045.332741/
				+02.039479+045.332473/
				+02.039479+045.332473/
				+02.040172+045.332320/
				+02.040172+045.332320/
				+02.040881+045.332285/
				+02.040881+045.332285/
				+02.041586+045.332370/
				+02.041586+045.332370/
				+02.042267+045.332571/
				+02.042267+045.332571/
				+02.042903+045.332885/
				+02.042903+045.332885/
				+02.043477+045.333301/
				+02.043477+045.333301/
				+02.043972+045.333807/
				+02.043972+045.333807/
				+02.044374+045.334389/
				+02.044374+045.334389/
				+02.044671+045.335030/
				+02.044671+045.335030/
				+02.044855+045.335712/
				+02.044855+045.335712/
				+02.044920+045.336415
			</Area>
			<Activations>
				<Activation H24="true" Start="0000" End="0000" />
			</Activations>
		</RestrictedArea>

		<RestrictedArea Type="Restricted" Name="HC (R)-2" AltitudeFloor="0" AltitudeCeiling="5000"
			DAIWEnabled="false" LinePattern="Solid">
			<Area>
				+01.989167+045.266389/
				+01.995000+045.274167/
				+01.995000+045.274167/
				+02.005556+045.268056/
				+02.005556+045.268056/
				+01.999445+045.259167/
				+01.999445+045.259167/
				+01.989167+045.266389/
				+01.989167+045.266389/
				+01.989167+045.266389
			</Area>
			<Activations>
				<Activation H24="true" Start="0000" End="0000" />
			</Activations>
		</RestrictedArea>

	</Areas>
</RestrictedAreas>